astrocalculator/__init__.py
astrocalculator/app.py
astrocalculator/calc.py
astrocalculator/static/style.css
astrocalculator/templates/index.html
AstroCalculator-0.2.1.dist-info/METADATA
AstroCalculator-0.2.1.dist-info/WHEEL
AstroCalculator-0.2.1.dist-info/entry_points.txt
AstroCalculator-0.2.1.dist-info/top_level.txt
AstroCalculator-0.2.1.dist-info/RECORD
