Metadata-Version: 2.1
Name: AstroCalculator
Version: 0.2.1
Summary: A locally hosted Flask application for astronomical calculations.
Home-page: https://github.com/chongchonghe/acap.git
Author: ChongChong He
Author-email: chongchong.he@anu.edu.au
Classifier: Programming Language :: Python :: 3
Classifier: License :: OSI Approved :: MIT License
Classifier: Operating System :: OS Independent
Requires-Python: >=3.6
Requires-Dist: flask>=2.0.0
Requires-Dist: sympy>=1.8
Requires-Dist: astropy>=4.0
Requires-Dist: gunicorn>=20.0.0
